[
  {
    "sentence": "너희 중에 고난 당하는 자가 있느냐 저는 기도할 것이요 즐거워하는 자가 있느냐 저는 찬송할지니라",
    "bookname": "약 5:13"
  },
  {
    "sentence": "너희 중에 병든 자가 있느냐 저는 교회의 장로들을 청할 것이요 그들은 주의 이름으로 기름을 바르며 위하여 기도할지니라",
    "bookname": "약 5:14"
  },
  {
    "sentence": "믿음의 기도는 병든 자를 구원하리니 주께서 저를 일으키시리라 혹시 죄를 범하였을지라도 사하심을 얻으리라",
    "bookname": "약 5:15"
  },
  {
    "sentence": "이러므로 너희 죄를 서로 고하며 병 낫기를 위하여 서로 기도하라 의인의 간구는 역사하는 힘이 많으니라",
    "bookname": "약 5:16"
  },
  {
    "sentence": "엘리야는 우리와 성정이 같은 사람이로되 저가 비 오지 않기를 간절히 기도한즉 삼년 육개월 동안 땅에 비가 아니오고",
    "bookname": "약 5:17"
  },
  {
    "sentence": "다시 기도한즉 하늘이 비를 주고 땅이 열매를 내었느니라",
    "bookname": "약 5:18"
  }
]