[
  {
    "sentence": "바울이 아덴에서 저희를 기다리다가 온 성에 우상이 가득한 것을 보고 마음에 분하여",
    "bookname": "행 17:16"
  },
  {
    "sentence": "회당에서는 유대인과 경건한 사람들과 또 저자에서는 날마다 만나는 사람들과 변론하니",
    "bookname": "행 17:17"
  },
  {
    "sentence": "어떤 에비구레오와 스도이고 철학자들도 바울과 쟁론할새 혹은 이르되 이 말장이가 무슨 말을 하고자 하느뇨 하고 혹은 이르되 이방 신들을 전하는 사람인가보다 하니 이는 바울이 예수와 또 몸의 부활 전함을 인함이러라",
    "bookname": "행 17:18"
  },
  {
    "sentence": "붙들어 가지고 아레오바고로 가며 말하기를 우리가 너의 말하는 이 새 교가 무엇인지 알수 있겠느냐",
    "bookname": "행 17:19"
  },
  {
    "sentence": "네가 무슨 이상한 것을 우리 귀에 들려 주니 그 무슨 뜻인지 알고자 하노라 하니",
    "bookname": "행 17:20"
  },
  {
    "sentence": "모든 아덴 사람과 거기서 나그네 된 외국인들이 가장 새로되는 것을 말하고 듣는 이외에 달리는 시간을 쓰지 않음이더라",
    "bookname": "행 17:21"
  },
  {
    "sentence": "바울이 아레오바고 가운데 서서 말하되 아덴 사람들아 너희를 보니 범사에 종교성이 많도다",
    "bookname": "행 17:22"
  },
  {
    "sentence": "내가 두루 다니며 너희의 위하는 것들을 보다가 알지 못하는 신에게라고 새긴 단도 보았으니 그런즉 너희가 알지 못하고 위하는 그것을 내가 너희에게 알게 하리라",
    "bookname": "행 17:23"
  },
  {
    "sentence": "우주와 그 가운데 있는 만유를 지으신 신께서는 천지의 주재시니 손으로 지은 전에 계시지 아니하시고",
    "bookname": "행 17:24"
  }
]