[
  {
    "sentence": "우리가 저에게서 듣고 너희에게 전하는 소식이 이것이니 곧 하나님은 빛이시라 그에게는 어두움이 조금도 없으시니라",
    "bookname": "요일 1:5"
  },
  {
    "sentence": "만일 우리가 하나님과 사귐이 있다 하고 어두운 가운데 행하면 거짓말을 하고 진리를 행치 아니함이거니와",
    "bookname": "요일 1:6"
  },
  {
    "sentence": "저가 빛 가운데 계신것 같이 우리도 빛 가운데 행하면 우리가 서로 사귐이 있고 그 아들 예수의 피가 우리를 모든 죄에서 깨끗하게 하실 것이요",
    "bookname": "요일 1:7"
  },
  {
    "sentence": "만일 우리가 죄 없다하면 스스로 속이고 또 진리가 우리 속에 있지 아니할 것이요",
    "bookname": "요일 1:8"
  },
  {
    "sentence": "만일 우리가 우리 죄를 자백하면 저는 미쁘시고 의로우사 우리 죄를 사하시며 모든 불의에서 우리를 깨끗케 하실 것이요",
    "bookname": "요일 1:9"
  },
  {
    "sentence": "만일 우리가 범죄하지 아니하였다 하면 하나님을 거짓말 하는 자로 만드는 것이니 또한 그의 말씀이 우리 속에 있지 아니하니라",
    "bookname": "요일 1:10"
  }
]